poeditor/__init__.py
poeditor/client.py
poeditor/dummy.py
poeditor/tests/__init__.py
poeditor/tests/test_client.py
poeditor-1.1.3.dist-info/LICENSE.md
poeditor-1.1.3.dist-info/METADATA
poeditor-1.1.3.dist-info/WHEEL
poeditor-1.1.3.dist-info/top_level.txt
poeditor-1.1.3.dist-info/RECORD
