Metadata-Version: 2.1
Name: poeditor
Version: 1.1.3
Summary: Client Interface for POEditor API (https://poeditor.com).
Home-page: https://github.com/sporteasy/python-poeditor
Author: Charles Vallantin Dulac, Karl Wan Nan Wo
Author-email: charles.vdulac@gmail.com, karl.wnw@gmail.com
License: MIT
Classifier: Development Status :: 5 - Production/Stable
Classifier: Environment :: Web Environment
Classifier: Intended Audience :: Developers
Classifier: License :: OSI Approved :: MIT License
Classifier: Operating System :: OS Independent
Classifier: Natural Language :: English
Classifier: Programming Language :: Python
Classifier: Programming Language :: Python :: 2.7
Classifier: Programming Language :: Python :: 3
Classifier: Topic :: Software Development :: Localization
License-File: LICENSE.md
Requires-Dist: requests
